{
  "project_info": {
    "project_number": "314988072682",
    "firebase_url": "https://best-reads-d214e.firebaseio.com",
    "project_id": "best-reads-d214e",
    "storage_bucket": "best-reads-d214e.appspot.com"
  },
  "client": [
    {
      "client_info": {
        "mobilesdk_app_id": "1:314988072682:android:c6912bfc73cb5f0bc51193",
        "android_client_info": {
          "package_name": "com.tanushree.bestreads"
        }
      },
      "oauth_client": [
        {
          "client_id": "314988072682-h49j8upr3nkr18qpusu7ggvdvppcsj28.apps.googleusercontent.com",
          "client_type": 3
        }
      ],
      "api_key": [
        {
          "current_key": "AIzaSyBQfPnsr1WIjv-1QR8a_xJNOU0PnD28R34"
        }
      ],
      "services": {
        "appinvite_service": {
          "other_platform_oauth_client": [
            {
              "client_id": "314988072682-h49j8upr3nkr18qpusu7ggvdvppcsj28.apps.googleusercontent.com",
              "client_type": 3
            }
          ]
        }
      }
    }
  ],
  "configuration_version": "1"
}